ustore/__init__.py
ustore-1.33.dist-info/LICENSE
ustore-1.33.dist-info/METADATA
ustore-1.33.dist-info/WHEEL
ustore-1.33.dist-info/top_level.txt
ustore-1.33.dist-info/RECORD
